hw/__init__.py
hw/generate.py
hw/generator.py
hw/picture.png
latex_converter_itmo_223215-0.0.1a0.dist-info/METADATA
latex_converter_itmo_223215-0.0.1a0.dist-info/WHEEL
latex_converter_itmo_223215-0.0.1a0.dist-info/top_level.txt
latex_converter_itmo_223215-0.0.1a0.dist-info/RECORD
