Metadata-Version: 2.1
Name: latex-converter-itmo-223215
Version: 0.0.1a0
Summary: Latex converter for ITMO
Home-page: https://github.com/example
Author: <Maxim Vukolov>
Author-email: <example@gmail.com>
